fsc/iohelper/__init__.py
fsc/iohelper/_iohelper.py
fsc/iohelper/_version.py
fsc/iohelper/version.txt
fsc/iohelper/encoding/__init__.py
fsc/iohelper/encoding/default.py
fsc.iohelper-1.0.3.dist-info/AUTHORS
fsc.iohelper-1.0.3.dist-info/METADATA
fsc.iohelper-1.0.3.dist-info/WHEEL
fsc.iohelper-1.0.3.dist-info/top_level.txt
fsc.iohelper-1.0.3.dist-info/RECORD
