Metadata-Version: 1.2
Name: fsc.iohelper
Version: 1.0.3
Summary: A tool for saving / loading data from file with a given encoding and decoding function.
